{
    "openHabUrl": "http://192.168.178.129:8080/rest",
    "filterByGroups": true,
	"groups": [
        {
            "name": "ContactSensors",
            "displayName": "Fenster und Tueren",
            "unit": "",
            "category": "contact"
        },
        {
            "name": "Lights",
            "displayName": "Lichter",
            "unit": "%",
            "category": "light"
        },
        {
            "name": "TemperatureSensors",
            "displayName": "Temperatur",
            "unit": "°C",
            "category": "temperature"
        },
        {
            "name": "MotionSensors",
            "displayName": "Bewegung",
            "unit": "",
            "category": "motion"
        },
        {
            "name": "BatteryStatus",
            "displayName": "Batterie",
            "unit": "%",
            "category": "battery"
        }
    ],
    "rooms": [
        {
            "group": "Wohnzimmer",
            "displayName": "Wohnzimmer"
        },
        {
            "group": "Kinderzimmer_Maria",
            "displayName": "Maria"
        },
        {
            "group": "Kinderzimmer_2",
            "displayName": "Tim"
        },
        {
            "group": "Schlafzimmer",
            "displayName": "Schlafzimmer"
        },
        {
            "group": "Bad",
            "displayName": "Bad"
        },
        {
            "group": "Flur",
            "displayName": "Flur"
        }
    ]
}
